sneks/__init__.py
sneks/compat.py
sneks/constants.py
sneks/get_client.py
sneks/parse_pdm.py
sneks/parse_poetry.py
sneks/plugin.py
sneks/wraps_args.py
sneks_sync-0.6.2.dist-info/LICENSE
sneks_sync-0.6.2.dist-info/METADATA
sneks_sync-0.6.2.dist-info/WHEEL
sneks_sync-0.6.2.dist-info/RECORD
