Metadata-Version: 2.1
Name: sneks-sync
Version: 0.6.2
Summary: Launch a Dask cluster from a virtual environment
License: MIT
Author: Gabe Joseph
Author-email: gjoseph92@gmail.com
Requires-Python: >=3.8.4,<4.0.0
Classifier: License :: OSI Approved :: MIT License
Classifier: Programming Language :: Python :: 3
Classifier: Programming Language :: Python :: 3.9
Classifier: Programming Language :: Python :: 3.10
Classifier: Programming Language :: Python :: 3.11
Requires-Dist: bokeh (>=2.4.2,<3)
Requires-Dist: cloudpickle (>=2.1.0,<3.0.0)
Requires-Dist: coiled (>=0.5.2,<0.6.0)
Requires-Dist: rich (>=12.4.4,<13.0.0)
Requires-Dist: setuptools (>=65.3.0)
Requires-Dist: tomli (>=2.0.1,<3.0.0)
